simbricks/cli/__init__.py
simbricks/cli/__main__.py
simbricks/cli/commands/admin.py
simbricks/cli/commands/audit.py
simbricks/cli/commands/instantiations.py
simbricks/cli/commands/namespaces.py
simbricks/cli/commands/org.py
simbricks/cli/commands/rg.py
simbricks/cli/commands/runners.py
simbricks/cli/commands/runs.py
simbricks/cli/commands/simulations.py
simbricks/cli/commands/systems.py
simbricks/cli/utils.py
simbricks_cli-0.3.6.dist-info/METADATA
simbricks_cli-0.3.6.dist-info/WHEEL
simbricks_cli-0.3.6.dist-info/entry_points.txt
simbricks_cli-0.3.6.dist-info/RECORD
