Metadata-Version: 2.3
Name: simbricks-cli
Version: 0.3.6
Summary: simbricks cli tool for communication with the SimBricks cloud
Author: Team SimBricks
Author-email: team@simbricks.io
Classifier: Programming Language :: Python :: 2
Classifier: Programming Language :: Python :: 2.7
Classifier: Programming Language :: Python :: 3
Classifier: Programming Language :: Python :: 3.4
Classifier: Programming Language :: Python :: 3.5
Classifier: Programming Language :: Python :: 3.6
Classifier: Programming Language :: Python :: 3.7
Classifier: Programming Language :: Python :: 3.8
Classifier: Programming Language :: Python :: 3.9
Classifier: Programming Language :: Python :: 3.10
Classifier: Programming Language :: Python :: 3.11
Classifier: Programming Language :: Python :: 3.12
Classifier: Programming Language :: Python :: 3.13
Requires-Dist: pytype (==2024.10.11)
Requires-Dist: rich (==13.9.4)
Requires-Dist: simbricks-client (>=0.3.6)
Requires-Dist: simbricks-orchestration (>=0.3.6)
Requires-Dist: typer (==0.15.4)
Project-URL: Homepage, https://www.simbricks.io/
